chaturbate_events/__init__.py
chaturbate_events/client.py
chaturbate_events/config.py
chaturbate_events/constants.py
chaturbate_events/exceptions.py
chaturbate_events/models.py
chaturbate_events/py.typed
chaturbate_events/router.py
chaturbate_events-1.11.0.dist-info/METADATA
chaturbate_events-1.11.0.dist-info/WHEEL
chaturbate_events-1.11.0.dist-info/licenses/LICENSE
chaturbate_events-1.11.0.dist-info/RECORD
