Metadata-Version: 2.4
Name: chaturbate-events
Version: 1.11.0
Summary: An asynchronous client for the Chaturbate Events API.
Project-URL: Homepage, https://github.com/MountainGod2/chaturbate-events
Project-URL: Documentation, https://github.com/MountainGod2/chaturbate-events#readme
Project-URL: Repository, https://github.com/MountainGod2/chaturbate-events.git
Project-URL: Changelog, https://github.com/MountainGod2/chaturbate-events/blob/main/CHANGELOG.md
Project-URL: Issue Tracker, https://github.com/MountainGod2/chaturbate-events/issues
Author-email: MountainGod2 <admin@reid.ca>
Maintainer-email: MountainGod2 <admin@reid.ca>
License: MIT
License-File: LICENSE
Keywords: api,async,chaturbate,client,events,real-time,streaming,webcam
Classifier: Development Status :: 4 - Beta
Classifier: Framework :: AsyncIO
Classifier: Framework :: Pydantic
Classifier: Intended Audience :: Developers
Classifier: License :: OSI Approved :: MIT License
Classifier: Operating System :: OS Independent
Classifier: Programming Language :: Python :: 3 :: Only
Classifier: Programming Language :: Python :: 3.11
Classifier: Programming Language :: Python :: 3.12
Classifier: Programming Language :: Python :: 3.13
Classifier: Topic :: Internet
Classifier: Topic :: Internet :: WWW/HTTP :: Dynamic Content
Classifier: Topic :: Software Development :: Libraries
Classifier: Topic :: Software Development :: Libraries :: Python Modules
Classifier: Typing :: Typed
Requires-Python: >=3.11
Requires-Dist: aiohttp-retry==2.9.1
Requires-Dist: aiohttp==3.12.15
Requires-Dist: aiolimiter==1.2.1
Requires-Dist: pydantic==2.11.9
